hypermea_negotiable_auth/__init__.py
hypermea_negotiable_auth/negotiable_auth.py
hypermea_negotiable_auth-0.9.9.dist-info/LICENSE
hypermea_negotiable_auth-0.9.9.dist-info/METADATA
hypermea_negotiable_auth-0.9.9.dist-info/WHEEL
hypermea_negotiable_auth-0.9.9.dist-info/top_level.txt
hypermea_negotiable_auth-0.9.9.dist-info/RECORD
