Metadata-Version: 2.2
Name: hypermea-negotiable-auth
Version: 0.9.9
Summary: Hypermea negotiable authentication
Home-page: https://github.com/pointw-dev/hypermea-negotiable-auth
Author: Michael Ottoson
Author-email: michael@pointw.com
License: MIT
Keywords: hypermea,eve,api,rest,auth,http
Classifier: Development Status :: 5 - Production/Stable
Classifier: License :: OSI Approved :: MIT License
Classifier: Programming Language :: Python
Classifier: Operating System :: OS Independent
Classifier: Framework :: Flask
Classifier: Intended Audience :: Developers
Classifier: Topic :: Internet :: WWW/HTTP :: HTTP Servers
Classifier: Topic :: Security
License-File: LICENSE
Requires-Dist: eve>=0.8.0
Requires-Dist: authparser>=1.0
Dynamic: author
Dynamic: author-email
Dynamic: classifier
Dynamic: description
Dynamic: description-content-type
Dynamic: home-page
Dynamic: keywords
Dynamic: license
Dynamic: requires-dist
Dynamic: summary
